filepass/__init__.py
filepass/filepass.py
filepass/filepass_config.py
filepass-1.0.2.dist-info/METADATA
filepass-1.0.2.dist-info/WHEEL
filepass-1.0.2.dist-info/licenses/LICENSE
filepass-1.0.2.dist-info/RECORD
