Metadata-Version: 2.3
Name: filepass
Version: 1.0.2
Summary: Wrapper around fs libraries to synchronized files between different system types including SMB, SFTP, FSTP.
Project-URL: Homepage, https://github.com/cityofkamloops/filepass
Project-URL: Bug Tracker, https://github.com/cityofkamloops/filepass/issues
Author-email: Orlund Norstrom <onorstrom@kamloops.ca>, Marco Lussetti <mlussetti@kamloops.ca>, Parul Parul <pparul@kamloops.ca>
License: Apache-2.0
License-File: LICENSE
Classifier: License :: OSI Approved :: Apache Software License
Classifier: Operating System :: OS Independent
Classifier: Programming Language :: Python :: 3
Requires-Python: >=3.10
Requires-Dist: appdirs==1.4.4
Requires-Dist: bcrypt==4.1.2
Requires-Dist: cffi==1.16.0
Requires-Dist: cryptography==42.0.2
Requires-Dist: fs-smbfs==1.0.7
Requires-Dist: fs-sshfs==1.0.2
Requires-Dist: fs==2.4.16
Requires-Dist: graypy==2.1.0
Requires-Dist: paramiko==3.4.0
Requires-Dist: property-cached==1.6.4
Requires-Dist: pyasn1==0.5.1
Requires-Dist: pycparser==2.21
Requires-Dist: pynacl==1.5.0
Requires-Dist: pysmb==1.2.9.1
Requires-Dist: six==1.16.0
Requires-Dist: tqdm==4.66.2
